{"cameraMode":{"drawMode":0,"name":"Shaded","section":"Shading Mode"},"sceneLighting":true,"audioPlay":false,"sceneViewState":{"m_AlwaysRefresh":false,"showFog":true,"showSkybox":true,"showFlares":true,"showImageEffects":true,"showParticleSystems":true,"showVisualEffectGraphs":true,"m_FxEnabled":true},"in2DMode":false,"pivot":{"x":383.0,"y":341.47430419921877,"z":0.0},"rotation":{"x":0.0029998780228197576,"y":-0.006000186316668987,"z":0.000018548627849668264,"w":0.9999805092811585},"size":571.0341186523438,"orthographic":false}